alibabacloud_aimiaobi20230801/__init__.py
alibabacloud_aimiaobi20230801/client.py
alibabacloud_aimiaobi20230801/models/__init__.py
alibabacloud_aimiaobi20230801/models/_add_audit_terms_request.py
alibabacloud_aimiaobi20230801/models/_add_audit_terms_response.py
alibabacloud_aimiaobi20230801/models/_add_audit_terms_response_body.py
alibabacloud_aimiaobi20230801/models/_add_audit_terms_shrink_request.py
alibabacloud_aimiaobi20230801/models/_add_dataset_document_request.py
alibabacloud_aimiaobi20230801/models/_add_dataset_document_response.py
alibabacloud_aimiaobi20230801/models/_add_dataset_document_response_body.py
alibabacloud_aimiaobi20230801/models/_add_dataset_document_shrink_request.py
alibabacloud_aimiaobi20230801/models/_async_create_clips_task_request.py
alibabacloud_aimiaobi20230801/models/_async_create_clips_task_response.py
alibabacloud_aimiaobi20230801/models/_async_create_clips_task_response_body.py
alibabacloud_aimiaobi20230801/models/_async_create_clips_task_shrink_request.py
alibabacloud_aimiaobi20230801/models/_async_create_clips_time_line_request.py
alibabacloud_aimiaobi20230801/models/_async_create_clips_time_line_response.py
alibabacloud_aimiaobi20230801/models/_async_create_clips_time_line_response_body.py
alibabacloud_aimiaobi20230801/models/_async_edit_timeline_request.py
alibabacloud_aimiaobi20230801/models/_async_edit_timeline_response.py
alibabacloud_aimiaobi20230801/models/_async_edit_timeline_response_body.py
alibabacloud_aimiaobi20230801/models/_async_edit_timeline_shrink_request.py
alibabacloud_aimiaobi20230801/models/_async_upload_tender_doc_request.py
alibabacloud_aimiaobi20230801/models/_async_upload_tender_doc_response.py
alibabacloud_aimiaobi20230801/models/_async_upload_tender_doc_response_body.py
alibabacloud_aimiaobi20230801/models/_async_upload_video_request.py
alibabacloud_aimiaobi20230801/models/_async_upload_video_response.py
alibabacloud_aimiaobi20230801/models/_async_upload_video_response_body.py
alibabacloud_aimiaobi20230801-1.38.5.dist-info/LICENSE
alibabacloud_aimiaobi20230801-1.38.5.dist-info/METADATA
alibabacloud_aimiaobi20230801-1.38.5.dist-info/WHEEL
alibabacloud_aimiaobi20230801-1.38.5.dist-info/top_level.txt
alibabacloud_aimiaobi20230801-1.38.5.dist-info/RECORD
